[
    {
        "plaintext" : "Order is heaven's first law.",
        "title" : "[150 points] Decode this quote by Alexander Pope which has been encoded using a Hill cipher."
    },
    {
        "plaintext" : "We convince by our presence.",
        "title" : "[200 points] Decode this quote by Walt Whitman which has been encoded using a Hill cipher."
    },
    {
        "plaintext" : "Darkness feeds on apathy.",
        "title" : "[150 points] Decode this quote by Dan Brown which has been encoded using a Hill cipher."
    },
    {
        "plaintext" : "Start small and keep going.",
        "title" : "[175 points] The following quote by Abhijit Naskar has been encoded using a Hill cipher."
    },
    {
        "plaintext" : "Wow that's amazing that he can bench two twenty five.",
        "title" : "[300 points] Decode this Hill cipher."
    },
    {
        "plaintext" : "Decrypting transposed text given arange for failts",
        "title" : "[225 points] Solve this Hill cipher about the railfence cipher."
    },
    {
        "plaintext" : "Tachistoscope",
        "title" : "[100 points] Decode this Hill cipher."
    },
    {
        "plaintext" : "Pochemuchka",
        "title" : "[200 points] Decode this Hill cipher."
    },
    {
        "plaintext" : "Eudaemonic",
        "title" : "[200 points] Decode this Hill cipher."
    },
    {
        "plaintext" : "Redox reaction",
        "title" : "[200 points] Decode this Hill cipher."
    },
    {
        "plaintext" : "Apartment complex",
        "title" : "[250 points] Decode this Hill cipher."
    },
    {
        "plaintext" : "Photosynthesis",
        "title" : "[150 points] Decode this Hill cipher."
    },
    {
        "plaintext" : "I never took a day off in my twenties not one",
        "title" : "[200 points] Decode this phrase by Bill Gates."
    },
    {
        "plaintext" : "Tigers roar",
        "title" : "[150 points] Decode the following phrase."
    },
    {
        "plaintext" : "In service of humanity",
        "title" : "[200 points] Decode this phrase."
    },
    {
        "plaintext" : "Expelliarmus",
        "title" : "[200 points] Decode this Hill cipher."
    },
    {
        "plaintext" : "It is noble and bright",
        "title" : "[250 points] Decode this phrase with the Hill cipher."
    },
    {
        "plaintext" : "The neutral signature",
        "title" : "[250 points] Solve this Hill cipher explaining what opponenets might not expect in Brawlhalla."
    },
    {
        "plaintext" : "A fun party game of coordination and speed",
        "title" : "[300 points] Decode this Hill cipher describing the game Unrailed."
    },
    {
        "plaintext" : "Professionals have standards",
        "title" : "[300 points] Decode this quote from Team Fortress 2."
    },
    {
        "plaintext" : "The only thing it could cost you is your life and you got that for free",
        "title" : "[300 points] Decode this quote from an NPC from the indie horro game Earthbound."
    },
    {
        "plaintext" : "The world is my country, all mankind are my brethren, and to do good is my religion.",
        "title" : "[400 points] The following quote from Thomas Paine needs to be decoded with the Hill cipher."
    },
    {
        "plaintext" : "The newspaper of utopia he had long ago decided would be terribly dull.",
        "title" : "[400 points] The following quote from 2001: A Space Odyssey was encoded with the Hill Cipher; decode it."
    },
    {
        "plaintext" : "A wise man can play the part of a clown but a clown can't play the part of a wise man.",
        "title" : "[500 points] Decode the following quote from Malcolm X which was encoded with the Hill cipher."
    },
    {
        "plaintext" : "Basketball",
        "title" : "[200 points] Decode the ciphertext using the Hill cipher."
    },
    {
        "plaintext" : "Squeezabilities",
        "title" : "[175 points] Decode the ciphertext using the Hill cipher."
    },
    {
        "plaintext" : "Vernacularization",
        "title" : "[250 points] Decode the ciphertext using the Hill cipher."
    },
    {
        "plaintext" : "Cats",
        "title" : "[100 points] Use the Hill cipher to decode the ciphertext."
    },
    {
        "plaintext" : "Jabba The Hutt",
        "title" : "[100 points] Use the Hill cipher to decode the ciphertext."
    }
]